ntnx_lifecycle_py_client/__init__.py
ntnx_lifecycle_py_client/api_client.py
ntnx_lifecycle_py_client/api_response.py
ntnx_lifecycle_py_client/configuration.py
ntnx_lifecycle_py_client/custom_retry.py
ntnx_lifecycle_py_client/rest.py
ntnx_lifecycle_py_client/api/__init__.py
ntnx_lifecycle_py_client/api/bundles_api.py
ntnx_lifecycle_py_client/api/config_api.py
ntnx_lifecycle_py_client/api/entities_api.py
ntnx_lifecycle_py_client/api/images_api.py
ntnx_lifecycle_py_client/api/inventory_api.py
ntnx_lifecycle_py_client/api/lcm_histories_api.py
ntnx_lifecycle_py_client/api/lcm_summaries_api.py
ntnx_lifecycle_py_client/api/notifications_api.py
ntnx_lifecycle_py_client/api/prechecks_api.py
ntnx_lifecycle_py_client/api/recommendations_api.py
ntnx_lifecycle_py_client/api/status_api.py
ntnx_lifecycle_py_client/api/upgrade_selections_api.py
ntnx_lifecycle_py_client/api/upgrades_api.py
ntnx_lifecycle_py_client/models/__init__.py
ntnx_lifecycle_py_client/models/OneOfcommon/__init__.py
ntnx_lifecycle_py_client/models/OneOfcommon/v1/__init__.py
ntnx_lifecycle_py_client/models/OneOfcommon/v1/config/KVPairvalue.py
ntnx_lifecycle_py_client/models/OneOfcommon/v1/config/__init__.py
ntnx_lifecycle_py_client/models/OneOflifecycle/__init__.py
ntnx_lifecycle_py_client/models/OneOflifecycle/v4/__init__.py
ntnx_lifecycle_py_client/models/OneOflifecycle/v4/common/Credentialcredential_detail.py
ntnx_lifecycle_py_client/models/OneOflifecycle/v4/common/VendorManagementCredentialcredential_spec.py
ntnx_lifecycle_py_client/models/OneOflifecycle/v4/common/__init__.py
ntnx_lifecycle_py_client/models/OneOflifecycle/v4/config/DomainProjectiondomain_manager.py
ntnx_lifecycle_py_client/models/OneOflifecycle/v4/config/Domaindomain_manager.py
ntnx_lifecycle_py_client/models/OneOflifecycle/v4/config/__init__.py
ntnx_lifecycle_py_client/models/OneOflifecycle/v4/error/ErrorResponseerror.py
ntnx_lifecycle_py_client/models/OneOflifecycle/v4/error/__init__.py
ntnx_lifecycle_py_client-4.2.1.dist-info/LICENSE.txt
ntnx_lifecycle_py_client-4.2.1.dist-info/METADATA
ntnx_lifecycle_py_client-4.2.1.dist-info/WHEEL
ntnx_lifecycle_py_client-4.2.1.dist-info/top_level.txt
ntnx_lifecycle_py_client-4.2.1.dist-info/RECORD
